{
  "task_id": "vue-element-plus-admin-441",
  "repo": "kailong321200875/vue-element-plus-admin",
  "worker": "worker-04",
  "status": "completed",
  "sess_id": "sess-20260427025956-b5a5bae10e614f048d8bf62b0a9e84cd",
  "expected_result_used": true,
  "duration_seconds": 241,
  "timestamp": "2026-04-27T03:04:01+08:00",
  "mano_cua": {
    "status": "COMPLETED",
    "total_steps": 25,
    "last_action": "DONE",
    "result": "unclear",
    "result_summary": "页面全局loading卡死，所有URL路径均显示loading spinner和ElementAdmin文字，从未加载出实际内容。尝试了刷新、硬刷新、直接导航到/#/login和/#/list/search-table均无效。与batch 26相同问题（vite-plugin-mock@2.9.6与Node23不兼容）",
    "last_reasoning": "The application is stuck in an infinite loading state. The spinner keeps animating but actual page content never loads. Confirmed across all URL paths including /#/, /#/login, /#/list/search-table. Browser-level page loading is complete but the app-level global loading never resolves."
  }
}
