{
  "task_id": "medium-editor-1047",
  "repo": "yabwe/medium-editor",
  "worker": "worker-02",
  "status": "completed",
  "sess_id": "sess-20260416123754-4446b5e0e40c4898bfa2eef567e23e99",
  "expected_result_used": true,
  "duration_seconds": 220,
  "timestamp": "2026-04-16T12:41:16+08:00",
  "mano_cua": {
    "status": "COMPLETED",
    "total_steps": 16,
    "last_action": "DONE",
    "result": "normal",
    "result_summary": "锚点预览功能正常：悬停链接文字显示 anchor preview 浮层，点击浮层打开链接编辑界面（非跳转），URL 可正常编辑",
    "last_reasoning": "I can see the URL \"http://example.com\" is now selected (highlighted in blue) in the input field. This confirms that the URL is fully editable. The link editing interface is working as expected."
  }
}
